fastdedupe/__init__.py
fastdedupe/__main__.py
fastdedupe/cli.py
fastdedupe/core.py
fastdedupe/tests/__init__.py
fastdedupe/tests/test_cli.py
fastdedupe/tests/test_core.py
fastdedupe/tests/test_main.py
fast_dedupe-0.1.1.dist-info/LICENSE
fast_dedupe-0.1.1.dist-info/METADATA
fast_dedupe-0.1.1.dist-info/WHEEL
fast_dedupe-0.1.1.dist-info/entry_points.txt
fast_dedupe-0.1.1.dist-info/top_level.txt
fast_dedupe-0.1.1.dist-info/RECORD
