Metadata-Version: 2.2
Name: fast-dedupe
Version: 0.1.1
Summary: Fast, Minimalist Text Deduplication Library for Python
Home-page: https://github.com/username/fast-dedupe
Author: Your Name
Author-email: your.email@example.com
Project-URL: Bug Reports, https://github.com/username/fast-dedupe/issues
Project-URL: Source, https://github.com/username/fast-dedupe
Project-URL: Documentation, https://github.com/username/fast-dedupe
Keywords: deduplication,fuzzy matching,text processing,data cleaning
Classifier: Development Status :: 4 - Beta
Classifier: Intended Audience :: Developers
Classifier: Intended Audience :: Science/Research
Classifier: License :: OSI Approved :: MIT License
Classifier: Programming Language :: Python :: 3
Classifier: Programming Language :: Python :: 3.8
Classifier: Programming Language :: Python :: 3.9
Classifier: Programming Language :: Python :: 3.10
Classifier: Programming Language :: Python :: 3.11
Classifier: Programming Language :: Python :: 3.12
Classifier: Topic :: Scientific/Engineering :: Artificial Intelligence
Classifier: Topic :: Software Development :: Libraries :: Python Modules
Classifier: Topic :: Text Processing :: Linguistic
Requires-Python: >=3.8
License-File: LICENSE
Requires-Dist: rapidfuzz<3.0.0,>=2.0.0
Dynamic: author
Dynamic: author-email
Dynamic: classifier
Dynamic: description
Dynamic: description-content-type
Dynamic: home-page
Dynamic: keywords
Dynamic: project-url
Dynamic: requires-dist
Dynamic: requires-python
Dynamic: summary
